ch/__init__.py
ch/sachi/__init__.py
ch/sachi/powermonitor/__init__.py
ch/sachi/powermonitor/config.py
ch/sachi/powermonitor/main.py
ch/sachi/powermonitor/powerdata_reader.py
ch/sachi/powermonitor/powermonitor_repository.py
ch/sachi/powermonitor/restService_powerdata.py
ch/sachi/victron_ble/__init__.py
ch/sachi/victron_ble/powermonitor_scanner.py
ch_sachi_powermonitor-0.1.9.dist-info/METADATA
ch_sachi_powermonitor-0.1.9.dist-info/WHEEL
ch_sachi_powermonitor-0.1.9.dist-info/entry_points.txt
ch_sachi_powermonitor-0.1.9.dist-info/RECORD
