Metadata-Version: 2.1
Name: ch.sachi.powermonitor
Version: 0.1.9
Summary: 
Author: Patrick Zbinden
Author-email: patrick+dev@zbinden-online.ch
Requires-Python: ==3.9.*
Classifier: Programming Language :: Python :: 3
Classifier: Programming Language :: Python :: 3.9
Requires-Dist: requests (>=2.31.0,<3.0.0)
Requires-Dist: victron-ble (>=0.6.0,<0.7.0)
